wowsnake/__init__.py
wowsnake/debil.py
wowsnake/launch.py
wowsnake/main.py
wowsnake/module_wowsnakes.py
wowsnake/wowsnakes.py
wowsnake-420.666.9333.dist-info/METADATA
wowsnake-420.666.9333.dist-info/WHEEL
wowsnake-420.666.9333.dist-info/top_level.txt
wowsnake-420.666.9333.dist-info/RECORD
