Metadata-Version: 2.1
Name: wowsnake
Version: 420.666.9333
Summary: 👁👄👁💬 import💢🚸🧞‍♀️/x  and play 🎃👻🍬
Home-page: https://youtube.com/@dclxviclan
Author: dclxviclan (dclxviclan)
Author-email: <dclxviclan@gmail.com>
Keywords: python,game,terminalgame,consolegame,snake,dclxviclan,shell,terminal,cmd
Classifier: Development Status :: 1 - Planning
Classifier: Intended Audience :: Developers
Classifier: Programming Language :: Python :: 3
Classifier: Operating System :: Unix
Classifier: Operating System :: MacOS :: MacOS X
Classifier: Operating System :: Microsoft :: Windows
Requires-Dist: colorama
